pyvoicekit/__init__.py
pyvoicekit/listen.py
pyvoicekit/speak.py
pyvoicekit-0.1.1.dist-info/licenses/LICENSE
pyvoicekit-0.1.1.dist-info/METADATA
pyvoicekit-0.1.1.dist-info/WHEEL
pyvoicekit-0.1.1.dist-info/top_level.txt
pyvoicekit-0.1.1.dist-info/RECORD
