Metadata-Version: 2.4
Name: pyvoicekit
Version: 0.1.1
Summary: Simple Python package for text-to-speech and speech-to-text
Home-page: https://github.com/firoziya/pyvoicekit
Author: Yash Kumar Firoziya
Classifier: Programming Language :: Python :: 3
Classifier: License :: OSI Approved :: MIT License
Classifier: Operating System :: OS Independent
Requires-Python: >=3.6
License-File: LICENSE
Requires-Dist: pyttsx3
Requires-Dist: SpeechRecognition
Requires-Dist: pyaudio
Dynamic: author
Dynamic: classifier
Dynamic: description
Dynamic: description-content-type
Dynamic: home-page
Dynamic: license-file
Dynamic: requires-dist
Dynamic: requires-python
Dynamic: summary
